{
  "attributes": [
    {
      "allow_nil?": false,
      "default": "fragment(\"uuid_generate_v4()\")",
      "generated?": false,
      "primary_key?": true,
      "references": null,
      "size": null,
      "source": "id",
      "type": "uuid"
    },
    {
      "allow_nil?": false,
      "default": "nil",
      "generated?": false,
      "primary_key?": false,
      "references": null,
      "size": null,
      "source": "name",
      "type": "text"
    },
    {
      "allow_nil?": true,
      "default": "nil",
      "generated?": false,
      "primary_key?": false,
      "references": null,
      "size": null,
      "source": "sex",
      "type": "text"
    },
    {
      "allow_nil?": true,
      "default": "nil",
      "generated?": false,
      "primary_key?": false,
      "references": null,
      "size": null,
      "source": "age",
      "type": "text"
    },
    {
      "allow_nil?": true,
      "default": "nil",
      "generated?": false,
      "primary_key?": false,
      "references": null,
      "size": null,
      "source": "fiv_felv_status",
      "type": "text"
    },
    {
      "allow_nil?": true,
      "default": "nil",
      "generated?": false,
      "primary_key?": false,
      "references": null,
      "size": null,
      "source": "health_status",
      "type": "text"
    },
    {
      "allow_nil?": true,
      "default": "nil",
      "generated?": false,
      "primary_key?": false,
      "references": null,
      "size": null,
      "source": "castrated",
      "type": "boolean"
    }
  ],
  "base_filter": null,
  "check_constraints": [],
  "custom_indexes": [],
  "custom_statements": [],
  "has_create_action": true,
  "hash": "08001587771D7CDBB4CCBE70598DB5D1D5CE54AA93C6B31F43B9C657EB9D9D99",
  "identities": [],
  "multitenancy": {
    "attribute": null,
    "global": null,
    "strategy": null
  },
  "repo": "Elixir.Kotkowo.Repo",
  "schema": null,
  "table": "cats"
}